{"event":"2022","owner_id":289461,"members":{"2674242":{"local_score":33,"id":2674242,"global_score":0,"completion_day_level":{"3":{"1":{"get_star_ts":1670252815,"star_index":1248896},"2":{"star_index":1252893,"get_star_ts":1670253825}},"4":{"2":{"star_index":1593160,"get_star_ts":1670345439},"1":{"get_star_ts":1670257149,"star_index":1266566}},"1":{"2":{"star_index":1217524,"get_star_ts":1670244911},"1":{"get_star_ts":1670242831,"star_index":1209817}},"2":{"1":{"get_star_ts":1670248195,"star_index":1230288},"2":{"star_index":1234113,"get_star_ts":1670249170}}},"stars":8,"name":"Patricio Touchard","last_star_ts":1670345439},"2547090":{"global_score":0,"id":2547090,"local_score":56,"stars":8,"completion_day_level":{"4":{"1":{"get_star_ts":1670160226,"star_index":942118},"2":{"get_star_ts":1670160711,"star_index":944166}},"3":{"1":{"star_index":935000,"get_star_ts":1670158490},"2":{"star_index":938087,"get_star_ts":1670159230}},"2":{"1":{"star_index":437961,"get_star_ts":1670001220},"2":{"star_index":440773,"get_star_ts":1670001984}},"1":{"1":{"get_star_ts":1669992389,"star_index":400727},"2":{"star_index":411397,"get_star_ts":1669994781}}},"last_star_ts":1670160711,"name":"CyriellePch"},"2317008":{"last_star_ts":1670491210,"name":"Thomas Rivollet","completion_day_level":{"3":{"2":{"star_index":667357,"get_star_ts":1670075969},"1":{"get_star_ts":1670075369,"star_index":665145}},"6":{"2":{"star_index":1507181,"get_star_ts":1670322010},"1":{"get_star_ts":1670321972,"star_index":1506994}},"2":{"1":{"star_index":304514,"get_star_ts":1669971254},"2":{"get_star_ts":1669971771,"star_index":307571}},"7":{"1":{"get_star_ts":1670419459,"star_index":1780496},"2":{"get_star_ts":1670422226,"star_index":1788137}},"4":{"2":{"star_index":1145366,"get_star_ts":1670227790},"1":{"star_index":1144386,"get_star_ts":1670227548}},"1":{"1":{"get_star_ts":1669881639,"star_index":0},"2":{"get_star_ts":1669881840,"star_index":730}},"8":{"1":{"star_index":1959634,"get_star_ts":1670488961},"2":{"star_index":1966809,"get_star_ts":1670491210}},"5":{"1":{"get_star_ts":1670231862,"star_index":1163530},"2":{"star_index":1166943,"get_star_ts":1670232563}}},"stars":16,"global_score":0,"id":2317008,"local_score":172},"2389927":{"completion_day_level":{"5":{"2":{"star_index":1512286,"get_star_ts":1670323264},"1":{"get_star_ts":1670323009,"star_index":1511305}},"7":{"2":{"star_index":1769278,"get_star_ts":1670415190},"1":{"get_star_ts":1670410145,"star_index":1755774}},"2":{"2":{"get_star_ts":1669973265,"star_index":316241},"1":{"get_star_ts":1669968729,"star_index":289868}},"1":{"1":{"get_star_ts":1669888790,"star_index":29565},"2":{"star_index":30273,"get_star_ts":1669888974}},"6":{"2":{"star_index":1544055,"get_star_ts":1670332229},"1":{"star_index":1543638,"get_star_ts":1670332111}},"3":{"2":{"get_star_ts":1670256334,"star_index":1263203},"1":{"star_index":1220350,"get_star_ts":1670245647}},"4":{"1":{"get_star_ts":1670316522,"star_index":1480895},"2":{"get_star_ts":1670316629,"star_index":1481449}}},"stars":14,"local_score":123,"id":2389927,"global_score":0,"name":"LouisNitag","last_star_ts":1670415190},"2308786":{"local_score":146,"id":2308786,"global_score":0,"completion_day_level":{"7":{"1":{"get_star_ts":1670509039,"star_index":2016909},"2":{"star_index":2020857,"get_star_ts":1670510395}},"2":{"1":{"star_index":290964,"get_star_ts":1669968936},"2":{"get_star_ts":1669969353,"star_index":293286}},"6":{"1":{"star_index":1482910,"get_star_ts":1670316900},"2":{"get_star_ts":1670317039,"star_index":1483662}},"3":{"1":{"star_index":901980,"get_star_ts":1670151042},"2":{"get_star_ts":1670151949,"star_index":906298}},"5":{"1":{"get_star_ts":1670241545,"star_index":1205122},"2":{"get_star_ts":1670244820,"star_index":1217164}},"1":{"2":{"get_star_ts":1669892769,"star_index":44384},"1":{"star_index":42925,"get_star_ts":1669892339}},"8":{"1":{"star_index":2030056,"get_star_ts":1670513588}},"4":{"2":{"star_index":965189,"get_star_ts":1670165941},"1":{"star_index":961323,"get_star_ts":1670164973}}},"stars":15,"name":"Loïc Eickmayer","last_star_ts":1670513588},"2411376":{"completion_day_level":{"1":{"2":{"star_index":68980,"get_star_ts":1669900345},"1":{"get_star_ts":1669900110,"star_index":68174}},"2":{"2":{"get_star_ts":1669974144,"star_index":321303},"1":{"star_index":311434,"get_star_ts":1669972459}},"3":{"2":{"star_index":1782628,"get_star_ts":1670420238},"1":{"star_index":1776003,"get_star_ts":1670417784}}},"stars":6,"id":2411376,"local_score":36,"global_score":0,"name":"Victor Archambault","last_star_ts":1670420238},"2323392":{"stars":0,"completion_day_level":{},"global_score":0,"local_score":0,"id":2323392,"last_star_ts":0,"name":"Jordan-Hardis"},"2527998":{"last_star_ts":1670246979,"name":"TheoRamousse","stars":5,"completion_day_level":{"3":{"1":{"star_index":1225558,"get_star_ts":1670246979}},"1":{"1":{"star_index":296461,"get_star_ts":1669969896},"2":{"get_star_ts":1669970490,"star_index":299877}},"2":{"2":{"star_index":329227,"get_star_ts":1669975590},"1":{"star_index":307423,"get_star_ts":1669971747}}},"global_score":0,"local_score":32,"id":2527998},"2309223":{"last_star_ts":1670150267,"name":"MGrebert","completion_day_level":{"1":{"1":{"star_index":472421,"get_star_ts":1670011781},"2":{"star_index":473427,"get_star_ts":1670012104}},"2":{"1":{"star_index":485022,"get_star_ts":1670015981},"2":{"star_index":489285,"get_star_ts":1670017468}},"3":{"1":{"get_star_ts":1670052506,"star_index":576496},"2":{"star_index":582097,"get_star_ts":1670054178}},"4":{"1":{"star_index":894486,"get_star_ts":1670149551},"2":{"get_star_ts":1670150267,"star_index":898083}}},"stars":8,"global_score":0,"id":2309223,"local_score":64},"289461":{"global_score":0,"local_score":144,"id":289461,"completion_day_level":{"1":{"2":{"star_index":4947,"get_star_ts":1669882974},"1":{"get_star_ts":1669882832,"star_index":4377}},"2":{"1":{"get_star_ts":1669969590,"star_index":294658},"2":{"star_index":333584,"get_star_ts":1669976476}},"8":{"1":{"star_index":2023271,"get_star_ts":1670511239}},"6":{"1":{"get_star_ts":1670315103,"star_index":1473271},"2":{"get_star_ts":1670315285,"star_index":1474223}},"3":{"2":{"star_index":580470,"get_star_ts":1670053697},"1":{"star_index":571085,"get_star_ts":1670050824}},"4":{"1":{"star_index":865441,"get_star_ts":1670143345},"2":{"star_index":866288,"get_star_ts":1670143546}},"5":{"2":{"get_star_ts":1670333526,"star_index":1548873},"1":{"star_index":1544752,"get_star_ts":1670332403}}},"stars":13,"last_star_ts":1670511239,"name":"Adrian Trif"},"2323306":{"last_star_ts":1670509415,"name":"Guillaume Payet","completion_day_level":{"5":{"1":{"get_star_ts":1670250684,"star_index":1240061},"2":{"star_index":1255308,"get_star_ts":1670254421}},"4":{"2":{"star_index":954745,"get_star_ts":1670163303},"1":{"star_index":948987,"get_star_ts":1670161908}},"1":{"2":{"get_star_ts":1669889898,"star_index":33839},"1":{"get_star_ts":1669886607,"star_index":20342}},"8":{"1":{"star_index":2018013,"get_star_ts":1670509415}},"7":{"1":{"get_star_ts":1670423949,"star_index":1793130},"2":{"star_index":1814224,"get_star_ts":1670431130}},"6":{"2":{"star_index":1511283,"get_star_ts":1670323003},"1":{"star_index":1510942,"get_star_ts":1670322912}},"3":{"2":{"get_star_ts":1670063543,"star_index":619012},"1":{"get_star_ts":1670060930,"star_index":607827}},"2":{"1":{"get_star_ts":1669973523,"star_index":317785},"2":{"star_index":319915,"get_star_ts":1669973905}}},"stars":15,"global_score":0,"local_score":145,"id":2323306},"2452774":{"completion_day_level":{},"stars":0,"id":2452774,"local_score":0,"global_score":0,"name":"Nornort","last_star_ts":0},"640957":{"stars":16,"completion_day_level":{"8":{"2":{"star_index":1963634,"get_star_ts":1670490210},"1":{"star_index":1960491,"get_star_ts":1670489229}},"1":{"2":{"get_star_ts":1669885584,"star_index":15900},"1":{"star_index":8559,"get_star_ts":1669883858}},"4":{"2":{"star_index":982013,"get_star_ts":1670170551},"1":{"star_index":980732,"get_star_ts":1670170196}},"5":{"2":{"get_star_ts":1670242755,"star_index":1209523},"1":{"get_star_ts":1670239709,"star_index":1198219}},"2":{"2":{"star_index":282989,"get_star_ts":1669967428},"1":{"star_index":280293,"get_star_ts":1669966913}},"3":{"2":{"get_star_ts":1670066307,"star_index":630567},"1":{"get_star_ts":1670064872,"star_index":624583}},"6":{"2":{"star_index":1505622,"get_star_ts":1670321654},"1":{"star_index":1504759,"get_star_ts":1670321449}},"7":{"1":{"get_star_ts":1670420304,"star_index":1782837},"2":{"get_star_ts":1670421531,"star_index":1786225}}},"global_score":0,"local_score":178,"id":640957,"last_star_ts":1670490210,"name":"Manami69"}}}